MANIFEST.in
setup.py
src/asm/__init__.py
src/asm.workflow.egg-info/PKG-INFO
src/asm.workflow.egg-info/SOURCES.txt
src/asm.workflow.egg-info/dependency_links.txt
src/asm.workflow.egg-info/not-zip-safe
src/asm.workflow.egg-info/requires.txt
src/asm.workflow.egg-info/top_level.txt
src/asm/workflow/__init__.py
src/asm/workflow/configure.zcml
src/asm/workflow/interfaces.py
src/asm/workflow/workflow.py
src/asm/workflow/generations/__init__.py
src/asm/workflow/generations/configure.zcml
src/asm/workflow/generations/evolve1.py
src/asm/workflow/generations/install.py
src/asm/workflow/tests/__init__.py
src/asm/workflow/tests/ftesting.zcml
src/asm/workflow/tests/test_workflow.py
src/asm/workflow/workflow_templates/inconsistentstatenotification.pt
src/asm/workflow/workflow_templates/publishmenuitem.pt