Metadata-Version: 1.0
Name: asm.workflow
Version: 0.1.7
Summary: Workflow extension for the Assembly CMS
Home-page: UNKNOWN
Author: Webcrew
Author-email: web@assembly.org
License: proprietary
Platform: UNKNOWN
